Metadata-Version: 2.1
Name: csr2transmart
Version: 0.4.0
Summary: Script to load CSR data to TranSMART
Home-page: https://github.com/thehyve/python_csr2transmart
Author: Gijs Kant
Author-email: gijs@thehyve.nl
License: MIT
Classifier: Development Status :: 2 - Pre-Alpha
Classifier: Intended Audience :: Developers
Classifier: Topic :: Scientific/Engineering :: Bio-Informatics
Classifier: License :: OSI Approved :: MIT License
Classifier: Natural Language :: English
Classifier: Programming Language :: Python :: 3
Classifier: Programming Language :: Python :: 3.7
Classifier: Programming Language :: Python :: 3.8
Classifier: Programming Language :: Python :: 3.9
Classifier: Programming Language :: Python :: 3.10
Requires-Python: >=3.7.0
License-File: LICENSE
Requires-Dist: importlib-metadata (<4.12,>=4.11)
Requires-Dist: click (<8.0,>=7.0)
Requires-Dist: transmart-loader (<1.5.0,>=1.4.1)
Requires-Dist: pydantic (<1.11,>=1.10)
Requires-Dist: python-dateutil (<2.9.0,>=2.8.0)
Requires-Dist: pandas (<1.4.3,>=1.3.5)
Requires-Dist: PyYAML (<6.1,>=5.4)
Provides-Extra: dev
Requires-Dist: prospector[with_pyroma] ; extra == 'dev'
Requires-Dist: yapf ; extra == 'dev'
Requires-Dist: isort ; extra == 'dev'
